MANIFEST.in
README.md
pyesg/__init__.py
pyesg/academy_rate_model.py
pyesg/interpolator.py
pyesg/stochastic_process.py
pyesg/utils.py
pyesg/version.py
pyesg/datasets/__init__.py
pyesg/datasets/academy_sample_scenario.csv
pyesg/datasets/us_stocks.csv
pyesg/datasets/ust_historical.csv
pyesg/interpolators/__init__.py
pyesg/interpolators/nelson_siegel.py
pyesg/interpolators/svensson.py
pyesg/processes/__init__.py
pyesg/processes/academy_rate_process.py
pyesg/processes/black_derman_toy_process.py
pyesg/processes/black_karasinski_process.py
pyesg/processes/cox_ingersoll_ross_process.py
pyesg/processes/geometric_brownian_motion.py
pyesg/processes/heston_process.py
pyesg/processes/ho_lee_process.py
pyesg/processes/ornstein_uhlenbeck_process.py
pyesg/processes/wiener_process.py
tests/__init__.py
tests/test_academy_rate_model.py
tests/test_datasets.py
tests/test_doctest.py
tests/test_interpolators.py
tests/test_processes.py
tests/test_utils.py
pyesg-0.1.5.dist-info/LICENSE
pyesg-0.1.5.dist-info/METADATA
pyesg-0.1.5.dist-info/WHEEL
pyesg-0.1.5.dist-info/top_level.txt
pyesg-0.1.5.dist-info/RECORD
