Metadata-Version: 2.1
Name: pyesg
Version: 0.1.5
Summary: Economic Scenario Generator for Python
Home-page: https://github.com/jason-ash/pyesg
Author: Jason Ash
Author-email: jason@ashanalytics.com
License: UNKNOWN
Platform: UNKNOWN
Classifier: Development Status :: 3 - Alpha
Classifier: License :: OSI Approved :: MIT License
Classifier: Topic :: Scientific/Engineering
Classifier: Programming Language :: Python
Classifier: Programming Language :: Python :: 3.6
Classifier: Programming Language :: Python :: 3.7
Classifier: Programming Language :: Python :: 3.8
Classifier: Programming Language :: Python :: 3.9
Requires-Python: >=3.6
Requires-Dist: numpy
Requires-Dist: pandas
Requires-Dist: scipy
Provides-Extra: dev
Requires-Dist: black (==19.10b0) ; extra == 'dev'
Requires-Dist: coverage (==5.2.1) ; extra == 'dev'
Requires-Dist: hypothesis (==5.24.4) ; extra == 'dev'
Requires-Dist: pre-commit (==2.6.0) ; extra == 'dev'
Requires-Dist: pylint (==2.6.0) ; extra == 'dev'
Requires-Dist: mypy (==0.782) ; extra == 'dev'
